MultiDown/__init__.py
MultiDown/__main__.py
MultiDown/downloader.py
MultiDown/webapp.py
multidown-0.4.0.dist-info/licenses/LICENSE
multidown-0.4.0.dist-info/METADATA
multidown-0.4.0.dist-info/WHEEL
multidown-0.4.0.dist-info/entry_points.txt
multidown-0.4.0.dist-info/top_level.txt
multidown-0.4.0.dist-info/RECORD
