Metadata-Version: 2.4
Name: MultiDown
Version: 0.4.0
Summary: A stylish cross-platform video downloader with web UI
Author: Bismoy Ghosh
License-File: LICENSE
Requires-Dist: flask
Requires-Dist: yt-dlp
Requires-Dist: rich
Requires-Dist: colorama
Requires-Dist: ffmpeg-python
Dynamic: author
Dynamic: license-file
Dynamic: requires-dist
Dynamic: summary
